LICENSE
prungo_util/__init__.py
prungo_util-0.1.10.dist-info/LICENSE
prungo_util-0.1.10.dist-info/WHEEL
prungo_util-0.1.10.dist-info/METADATA
prungo_util-0.1.10.dist-info/RECORD
